promptbook/__init__.py
promptbook/book_manager.py
promptbook/cli.py
promptbook/config_manager.py
promptbook/git_utils.py
promptbook/loader.py
promptbook/processor.py
promptbook/utils.py
promptbook/validator.py
promptbook-0.3.0.dist-info/METADATA
promptbook-0.3.0.dist-info/WHEEL
promptbook-0.3.0.dist-info/entry_points.txt
promptbook-0.3.0.dist-info/top_level.txt
promptbook-0.3.0.dist-info/RECORD
