Metadata-Version: 2.2
Name: promptbook
Version: 0.3.0
Summary: A prompt library and execution tool
Author-email: Your Name <your.email@example.com>
License: MIT
Requires-Python: >=3.7
Requires-Dist: requests
Requires-Dist: pyyaml
